{"interfaceLanguages":{"swift":[{"children":[{"title":"Classes","type":"groupMarker"},{"children":[{"title":"Instance Methods","type":"groupMarker"},{"path":"\/documentation\/messenger\/appdelegate\/application(_:configurationforconnecting:options:)","title":"func application(UIApplication, configurationForConnecting: UISceneSession, options: UIScene.ConnectionOptions) -> UISceneConfiguration","type":"method"},{"path":"\/documentation\/messenger\/appdelegate\/application(_:diddiscardscenesessions:)","title":"func application(UIApplication, didDiscardSceneSessions: Set<UISceneSession>)","type":"method"},{"path":"\/documentation\/messenger\/appdelegate\/application(_:didfinishlaunchingwithoptions:)","title":"func application(UIApplication, didFinishLaunchingWithOptions: [UIApplication.LaunchOptionsKey : Any]?) -> Bool","type":"method"},{"title":"Default Implementations","type":"groupMarker"},{"children":[{"title":"Type Methods","type":"groupMarker"},{"path":"\/documentation\/messenger\/appdelegate\/main()","title":"static func main()","type":"method"}],"path":"\/documentation\/messenger\/appdelegate\/uiapplicationdelegate-implementations","title":"UIApplicationDelegate Implementations","type":"symbol"}],"path":"\/documentation\/messenger\/appdelegate","title":"AppDelegate","type":"class"},{"children":[{"title":"Initializers","type":"groupMarker"},{"path":"\/documentation\/messenger\/chatviewcontroller\/init(coder:)","title":"init?(coder: NSCoder)","type":"init"},{"path":"\/documentation\/messenger\/chatviewcontroller\/init(with:id:)","title":"init(with: String, id: String?)","type":"init"},{"title":"Instance Properties","type":"groupMarker"},{"path":"\/documentation\/messenger\/chatviewcontroller\/isnewconversation","title":"var isNewConversation: Bool","type":"property"},{"path":"\/documentation\/messenger\/chatviewcontroller\/messages","title":"var messages: [Message]","type":"property"},{"path":"\/documentation\/messenger\/chatviewcontroller\/otheruseremail","title":"let otherUserEmail: String","type":"property"},{"title":"Instance Methods","type":"groupMarker"},{"path":"\/documentation\/messenger\/chatviewcontroller\/viewdidappear(_:)","title":"func viewDidAppear(Bool)","type":"method"},{"path":"\/documentation\/messenger\/chatviewcontroller\/viewdidload()","title":"func viewDidLoad()","type":"method"},{"title":"Type Properties","type":"groupMarker"},{"path":"\/documentation\/messenger\/chatviewcontroller\/dateformatter","title":"static let dateFormatter: DateFormatter","type":"property"},{"title":"Default Implementations","type":"groupMarker"},{"children":[{"title":"Instance Methods","type":"groupMarker"},{"path":"\/documentation\/messenger\/chatviewcontroller\/inputbar(_:didchangeintrinsiccontentto:)","title":"func inputBar(InputBarAccessoryView, didChangeIntrinsicContentTo: CGSize)","type":"method"},{"path":"\/documentation\/messenger\/chatviewcontroller\/inputbar(_:didpresssendbuttonwith:)","title":"func inputBar(InputBarAccessoryView, didPressSendButtonWith: String)","type":"method"},{"path":"\/documentation\/messenger\/chatviewcontroller\/inputbar(_:didswipetextviewwith:)","title":"func inputBar(InputBarAccessoryView, didSwipeTextViewWith: UISwipeGestureRecognizer)","type":"method"},{"path":"\/documentation\/messenger\/chatviewcontroller\/inputbar(_:textviewtextdidchangeto:)","title":"func inputBar(InputBarAccessoryView, textViewTextDidChangeTo: String)","type":"method"}],"path":"\/documentation\/messenger\/chatviewcontroller\/inputbaraccessoryviewdelegate-implementations","title":"InputBarAccessoryViewDelegate Implementations","type":"symbol"},{"children":[{"title":"Instance Methods","type":"groupMarker"},{"path":"\/documentation\/messenger\/chatviewcontroller\/didpauseaudio(in:)","title":"func didPauseAudio(in: AudioMessageCell)","type":"method"},{"path":"\/documentation\/messenger\/chatviewcontroller\/didstartaudio(in:)","title":"func didStartAudio(in: AudioMessageCell)","type":"method"},{"path":"\/documentation\/messenger\/chatviewcontroller\/didstopaudio(in:)","title":"func didStopAudio(in: AudioMessageCell)","type":"method"},{"path":"\/documentation\/messenger\/chatviewcontroller\/didtapaccessoryview(in:)","title":"func didTapAccessoryView(in: MessageCollectionViewCell)","type":"method"},{"path":"\/documentation\/messenger\/chatviewcontroller\/didtapavatar(in:)","title":"func didTapAvatar(in: MessageCollectionViewCell)","type":"method"},{"path":"\/documentation\/messenger\/chatviewcontroller\/didtapbackground(in:)","title":"func didTapBackground(in: MessageCollectionViewCell)","type":"method"},{"path":"\/documentation\/messenger\/chatviewcontroller\/didtapcellbottomlabel(in:)","title":"func didTapCellBottomLabel(in: MessageCollectionViewCell)","type":"method"},{"path":"\/documentation\/messenger\/chatviewcontroller\/didtapcelltoplabel(in:)","title":"func didTapCellTopLabel(in: MessageCollectionViewCell)","type":"method"},{"path":"\/documentation\/messenger\/chatviewcontroller\/didtapimage(in:)","title":"func didTapImage(in: MessageCollectionViewCell)","type":"method"},{"path":"\/documentation\/messenger\/chatviewcontroller\/didtapmessage(in:)","title":"func didTapMessage(in: MessageCollectionViewCell)","type":"method"},{"path":"\/documentation\/messenger\/chatviewcontroller\/didtapmessagebottomlabel(in:)","title":"func didTapMessageBottomLabel(in: MessageCollectionViewCell)","type":"method"},{"path":"\/documentation\/messenger\/chatviewcontroller\/didtapmessagetoplabel(in:)","title":"func didTapMessageTopLabel(in: MessageCollectionViewCell)","type":"method"},{"path":"\/documentation\/messenger\/chatviewcontroller\/didtapplaybutton(in:)","title":"func didTapPlayButton(in: AudioMessageCell)","type":"method"}],"path":"\/documentation\/messenger\/chatviewcontroller\/messagecelldelegate-implementations","title":"MessageCellDelegate Implementations","type":"symbol"},{"children":[{"title":"Instance Methods","type":"groupMarker"},{"path":"\/documentation\/messenger\/chatviewcontroller\/didselectaddress(_:)","title":"func didSelectAddress([String : String])","type":"method"},{"path":"\/documentation\/messenger\/chatviewcontroller\/didselectcustom(_:match:)","title":"func didSelectCustom(String, match: String?)","type":"method"},{"path":"\/documentation\/messenger\/chatviewcontroller\/didselectdate(_:)","title":"func didSelectDate(Date)","type":"method"},{"path":"\/documentation\/messenger\/chatviewcontroller\/didselecthashtag(_:)","title":"func didSelectHashtag(String)","type":"method"},{"path":"\/documentation\/messenger\/chatviewcontroller\/didselectmention(_:)","title":"func didSelectMention(String)","type":"method"},{"path":"\/documentation\/messenger\/chatviewcontroller\/didselectphonenumber(_:)","title":"func didSelectPhoneNumber(String)","type":"method"},{"path":"\/documentation\/messenger\/chatviewcontroller\/didselecttransitinformation(_:)","title":"func didSelectTransitInformation([String : String])","type":"method"},{"path":"\/documentation\/messenger\/chatviewcontroller\/didselecturl(_:)","title":"func didSelectURL(URL)","type":"method"}],"path":"\/documentation\/messenger\/chatviewcontroller\/messagelabeldelegate-implementations","title":"MessageLabelDelegate Implementations","type":"symbol"},{"children":[{"title":"Instance Properties","type":"groupMarker"},{"path":"\/documentation\/messenger\/chatviewcontroller\/currentsender","title":"var currentSender: SenderType","type":"property"},{"title":"Instance Methods","type":"groupMarker"},{"path":"\/documentation\/messenger\/chatviewcontroller\/audiocell(for:at:in:)","title":"func audioCell(for: MessageType, at: IndexPath, in: MessagesCollectionView) -> UICollectionViewCell?","type":"method"},{"path":"\/documentation\/messenger\/chatviewcontroller\/cellbottomlabelattributedtext(for:at:)","title":"func cellBottomLabelAttributedText(for: MessageType, at: IndexPath) -> NSAttributedString?","type":"method"},{"path":"\/documentation\/messenger\/chatviewcontroller\/celltoplabelattributedtext(for:at:)","title":"func cellTopLabelAttributedText(for: MessageType, at: IndexPath) -> NSAttributedString?","type":"method"},{"path":"\/documentation\/messenger\/chatviewcontroller\/contactcell(for:at:in:)","title":"func contactCell(for: MessageType, at: IndexPath, in: MessagesCollectionView) -> UICollectionViewCell?","type":"method"},{"path":"\/documentation\/messenger\/chatviewcontroller\/customcell(for:at:in:)","title":"func customCell(for: MessageType, at: IndexPath, in: MessagesCollectionView) -> UICollectionViewCell","type":"method"},{"path":"\/documentation\/messenger\/chatviewcontroller\/isfromcurrentsender(message:)","title":"func isFromCurrentSender(message: MessageType) -> Bool","type":"method"},{"path":"\/documentation\/messenger\/chatviewcontroller\/locationcell(for:at:in:)","title":"func locationCell(for: MessageType, at: IndexPath, in: MessagesCollectionView) -> UICollectionViewCell?","type":"method"},{"path":"\/documentation\/messenger\/chatviewcontroller\/messagebottomlabelattributedtext(for:at:)","title":"func messageBottomLabelAttributedText(for: MessageType, at: IndexPath) -> NSAttributedString?","type":"method"},{"path":"\/documentation\/messenger\/chatviewcontroller\/messageforitem(at:in:)","title":"func messageForItem(at: IndexPath, in: MessagesCollectionView) -> MessageType","type":"method"},{"path":"\/documentation\/messenger\/chatviewcontroller\/messagetimestamplabelattributedtext(for:at:)","title":"func messageTimestampLabelAttributedText(for: MessageType, at: IndexPath) -> NSAttributedString?","type":"method"},{"path":"\/documentation\/messenger\/chatviewcontroller\/messagetoplabelattributedtext(for:at:)","title":"func messageTopLabelAttributedText(for: MessageType, at: IndexPath) -> NSAttributedString?","type":"method"},{"path":"\/documentation\/messenger\/chatviewcontroller\/numberofitems(insection:in:)","title":"func numberOfItems(inSection: Int, in: MessagesCollectionView) -> Int","type":"method"},{"path":"\/documentation\/messenger\/chatviewcontroller\/numberofsections(in:)","title":"func numberOfSections(in: MessagesCollectionView) -> Int","type":"method"},{"path":"\/documentation\/messenger\/chatviewcontroller\/photocell(for:at:in:)","title":"func photoCell(for: MessageType, at: IndexPath, in: MessagesCollectionView) -> UICollectionViewCell?","type":"method"},{"path":"\/documentation\/messenger\/chatviewcontroller\/textcell(for:at:in:)","title":"func textCell(for: MessageType, at: IndexPath, in: MessagesCollectionView) -> UICollectionViewCell?","type":"method"},{"path":"\/documentation\/messenger\/chatviewcontroller\/typingindicator(at:in:)","title":"func typingIndicator(at: IndexPath, in: MessagesCollectionView) -> UICollectionViewCell","type":"method"}],"path":"\/documentation\/messenger\/chatviewcontroller\/messagesdatasource-implementations","title":"MessagesDataSource Implementations","type":"symbol"},{"children":[{"title":"Instance Methods","type":"groupMarker"},{"path":"\/documentation\/messenger\/chatviewcontroller\/animationblockforlocation(message:at:in:)","title":"func animationBlockForLocation(message: MessageType, at: IndexPath, in: MessagesCollectionView) -> ((UIImageView) -> Void)?","type":"method"},{"path":"\/documentation\/messenger\/chatviewcontroller\/annotationviewforlocation(message:at:in:)","title":"func annotationViewForLocation(message: MessageType, at: IndexPath, in: MessagesCollectionView) -> MKAnnotationView?","type":"method"},{"path":"\/documentation\/messenger\/chatviewcontroller\/audioprogresstextformat(_:for:in:)","title":"func audioProgressTextFormat(Float, for: AudioMessageCell, in: MessagesCollectionView) -> String","type":"method"},{"path":"\/documentation\/messenger\/chatviewcontroller\/audiotintcolor(for:at:in:)","title":"func audioTintColor(for: MessageType, at: IndexPath, in: MessagesCollectionView) -> UIColor","type":"method"},{"path":"\/documentation\/messenger\/chatviewcontroller\/backgroundcolor(for:at:in:)","title":"func backgroundColor(for: MessageType, at: IndexPath, in: MessagesCollectionView) -> UIColor","type":"method"},{"path":"\/documentation\/messenger\/chatviewcontroller\/configureaccessoryview(_:for:at:in:)","title":"func configureAccessoryView(UIView, for: MessageType, at: IndexPath, in: MessagesCollectionView)","type":"method"},{"path":"\/documentation\/messenger\/chatviewcontroller\/configureaudiocell(_:message:)","title":"func configureAudioCell(AudioMessageCell, message: MessageType)","type":"method"},{"path":"\/documentation\/messenger\/chatviewcontroller\/configureavatarview(_:for:at:in:)","title":"func configureAvatarView(AvatarView, for: MessageType, at: IndexPath, in: MessagesCollectionView)","type":"method"},{"path":"\/documentation\/messenger\/chatviewcontroller\/configurelinkpreviewimageview(_:for:at:in:)","title":"func configureLinkPreviewImageView(UIImageView, for: MessageType, at: IndexPath, in: MessagesCollectionView)","type":"method"},{"path":"\/documentation\/messenger\/chatviewcontroller\/configuremediamessageimageview(_:for:at:in:)","title":"func configureMediaMessageImageView(UIImageView, for: MessageType, at: IndexPath, in: MessagesCollectionView)","type":"method"},{"path":"\/documentation\/messenger\/chatviewcontroller\/detectorattributes(for:and:at:)","title":"func detectorAttributes(for: DetectorType, and: MessageType, at: IndexPath) -> [NSAttributedString.Key : Any]","type":"method"},{"path":"\/documentation\/messenger\/chatviewcontroller\/enableddetectors(for:at:in:)","title":"func enabledDetectors(for: MessageType, at: IndexPath, in: MessagesCollectionView) -> [DetectorType]","type":"method"},{"path":"\/documentation\/messenger\/chatviewcontroller\/messagefooterview(for:in:)","title":"func messageFooterView(for: IndexPath, in: MessagesCollectionView) -> MessageReusableView","type":"method"},{"path":"\/documentation\/messenger\/chatviewcontroller\/messageheaderview(for:in:)","title":"func messageHeaderView(for: IndexPath, in: MessagesCollectionView) -> MessageReusableView","type":"method"},{"path":"\/documentation\/messenger\/chatviewcontroller\/messagestyle(for:at:in:)","title":"func messageStyle(for: MessageType, at: IndexPath, in: MessagesCollectionView) -> MessageStyle","type":"method"},{"path":"\/documentation\/messenger\/chatviewcontroller\/snapshotoptionsforlocation(message:at:in:)","title":"func snapshotOptionsForLocation(message: MessageType, at: IndexPath, in: MessagesCollectionView) -> LocationMessageSnapshotOptions","type":"method"},{"path":"\/documentation\/messenger\/chatviewcontroller\/textcolor(for:at:in:)","title":"func textColor(for: MessageType, at: IndexPath, in: MessagesCollectionView) -> UIColor","type":"method"}],"path":"\/documentation\/messenger\/chatviewcontroller\/messagesdisplaydelegate-implementations","title":"MessagesDisplayDelegate Implementations","type":"symbol"},{"children":[{"title":"Instance Methods","type":"groupMarker"},{"path":"\/documentation\/messenger\/chatviewcontroller\/attributedtextcellsizecalculator(for:at:in:)","title":"func attributedTextCellSizeCalculator(for: MessageType, at: IndexPath, in: MessagesCollectionView) -> CellSizeCalculator?","type":"method"},{"path":"\/documentation\/messenger\/chatviewcontroller\/audiocellsizecalculator(for:at:in:)","title":"func audioCellSizeCalculator(for: MessageType, at: IndexPath, in: MessagesCollectionView) -> CellSizeCalculator?","type":"method"},{"path":"\/documentation\/messenger\/chatviewcontroller\/avatarposition(for:at:in:)","title":"func avatarPosition(for: MessageType, at: IndexPath, in: MessagesCollectionView) -> AvatarPosition","type":"method"},{"path":"\/documentation\/messenger\/chatviewcontroller\/avatarsize(for:at:in:)-3j1bt","title":"func avatarSize(for: MessageType, at: IndexPath, in: MessagesCollectionView) -> CGSize","type":"method"},{"path":"\/documentation\/messenger\/chatviewcontroller\/avatarsize(for:at:in:)-5qyhm","title":"func avatarSize(for: MessageType, at: IndexPath, in: MessagesCollectionView) -> CGSize?","type":"method"},{"path":"\/documentation\/messenger\/chatviewcontroller\/cellbottomlabelalignment(for:at:in:)","title":"func cellBottomLabelAlignment(for: MessageType, at: IndexPath, in: MessagesCollectionView) -> LabelAlignment","type":"method"},{"path":"\/documentation\/messenger\/chatviewcontroller\/cellbottomlabelheight(for:at:in:)","title":"func cellBottomLabelHeight(for: MessageType, at: IndexPath, in: MessagesCollectionView) -> CGFloat","type":"method"},{"path":"\/documentation\/messenger\/chatviewcontroller\/celltoplabelalignment(for:at:in:)","title":"func cellTopLabelAlignment(for: MessageType, at: IndexPath, in: MessagesCollectionView) -> LabelAlignment","type":"method"},{"path":"\/documentation\/messenger\/chatviewcontroller\/celltoplabelheight(for:at:in:)","title":"func cellTopLabelHeight(for: MessageType, at: IndexPath, in: MessagesCollectionView) -> CGFloat","type":"method"},{"path":"\/documentation\/messenger\/chatviewcontroller\/contactcellsizecalculator(for:at:in:)","title":"func contactCellSizeCalculator(for: MessageType, at: IndexPath, in: MessagesCollectionView) -> CellSizeCalculator?","type":"method"},{"path":"\/documentation\/messenger\/chatviewcontroller\/customcellsizecalculator(for:at:in:)","title":"func customCellSizeCalculator(for: MessageType, at: IndexPath, in: MessagesCollectionView) -> CellSizeCalculator","type":"method"},{"path":"\/documentation\/messenger\/chatviewcontroller\/emojicellsizecalculator(for:at:in:)","title":"func emojiCellSizeCalculator(for: MessageType, at: IndexPath, in: MessagesCollectionView) -> CellSizeCalculator?","type":"method"},{"path":"\/documentation\/messenger\/chatviewcontroller\/footerviewsize(for:in:)","title":"func footerViewSize(for: Int, in: MessagesCollectionView) -> CGSize","type":"method"},{"path":"\/documentation\/messenger\/chatviewcontroller\/headerviewsize(for:in:)","title":"func headerViewSize(for: Int, in: MessagesCollectionView) -> CGSize","type":"method"},{"path":"\/documentation\/messenger\/chatviewcontroller\/heightforlocation(message:at:with:in:)","title":"func heightForLocation(message: MessageType, at: IndexPath, with: CGFloat, in: MessagesCollectionView) -> CGFloat","type":"method"},{"path":"\/documentation\/messenger\/chatviewcontroller\/heightformedia(message:at:with:in:)","title":"func heightForMedia(message: MessageType, at: IndexPath, with: CGFloat, in: MessagesCollectionView) -> CGFloat","type":"method"},{"path":"\/documentation\/messenger\/chatviewcontroller\/locationcellsizecalculator(for:at:in:)","title":"func locationCellSizeCalculator(for: MessageType, at: IndexPath, in: MessagesCollectionView) -> CellSizeCalculator?","type":"method"},{"path":"\/documentation\/messenger\/chatviewcontroller\/messagebottomlabelalignment(for:at:in:)","title":"func messageBottomLabelAlignment(for: MessageType, at: IndexPath, in: MessagesCollectionView) -> LabelAlignment?","type":"method"},{"path":"\/documentation\/messenger\/chatviewcontroller\/messagebottomlabelheight(for:at:in:)","title":"func messageBottomLabelHeight(for: MessageType, at: IndexPath, in: MessagesCollectionView) -> CGFloat","type":"method"},{"path":"\/documentation\/messenger\/chatviewcontroller\/messagelabelinset(for:at:in:)","title":"func messageLabelInset(for: MessageType, at: IndexPath, in: MessagesCollectionView) -> UIEdgeInsets","type":"method"},{"path":"\/documentation\/messenger\/chatviewcontroller\/messagepadding(for:at:in:)","title":"func messagePadding(for: MessageType, at: IndexPath, in: MessagesCollectionView) -> UIEdgeInsets","type":"method"},{"path":"\/documentation\/messenger\/chatviewcontroller\/messagetoplabelalignment(for:at:in:)","title":"func messageTopLabelAlignment(for: MessageType, at: IndexPath, in: MessagesCollectionView) -> LabelAlignment?","type":"method"},{"path":"\/documentation\/messenger\/chatviewcontroller\/messagetoplabelheight(for:at:in:)","title":"func messageTopLabelHeight(for: MessageType, at: IndexPath, in: MessagesCollectionView) -> CGFloat","type":"method"},{"path":"\/documentation\/messenger\/chatviewcontroller\/photocellsizecalculator(for:at:in:)","title":"func photoCellSizeCalculator(for: MessageType, at: IndexPath, in: MessagesCollectionView) -> CellSizeCalculator?","type":"method"},{"path":"\/documentation\/messenger\/chatviewcontroller\/shouldcachelayoutattributes(for:)","title":"func shouldCacheLayoutAttributes(for: MessageType) -> Bool","type":"method"},{"path":"\/documentation\/messenger\/chatviewcontroller\/textcellsizecalculator(for:at:in:)","title":"func textCellSizeCalculator(for: MessageType, at: IndexPath, in: MessagesCollectionView) -> CellSizeCalculator?","type":"method"},{"path":"\/documentation\/messenger\/chatviewcontroller\/typingindicatorviewsize(for:)","title":"func typingIndicatorViewSize(for: MessagesCollectionViewFlowLayout) -> CGSize","type":"method"},{"path":"\/documentation\/messenger\/chatviewcontroller\/typingindicatorviewtopinset(in:)","title":"func typingIndicatorViewTopInset(in: MessagesCollectionView) -> CGFloat","type":"method"},{"path":"\/documentation\/messenger\/chatviewcontroller\/videocellsizecalculator(for:at:in:)","title":"func videoCellSizeCalculator(for: MessageType, at: IndexPath, in: MessagesCollectionView) -> CellSizeCalculator?","type":"method"},{"path":"\/documentation\/messenger\/chatviewcontroller\/widthforlocation(message:at:with:in:)","title":"func widthForLocation(message: MessageType, at: IndexPath, with: CGFloat, in: MessagesCollectionView) -> CGFloat","type":"method"},{"path":"\/documentation\/messenger\/chatviewcontroller\/widthformedia(message:at:with:in:)","title":"func widthForMedia(message: MessageType, at: IndexPath, with: CGFloat, in: MessagesCollectionView) -> CGFloat","type":"method"}],"path":"\/documentation\/messenger\/chatviewcontroller\/messageslayoutdelegate-implementations","title":"MessagesLayoutDelegate Implementations","type":"symbol"},{"children":[{"title":"Instance Methods","type":"groupMarker"},{"path":"\/documentation\/messenger\/chatviewcontroller\/imagepickercontroller(_:didfinishpickingmediawithinfo:)","title":"func imagePickerController(UIImagePickerController, didFinishPickingMediaWithInfo: [UIImagePickerController.InfoKey : Any])","type":"method"},{"path":"\/documentation\/messenger\/chatviewcontroller\/imagepickercontrollerdidcancel(_:)","title":"func imagePickerControllerDidCancel(UIImagePickerController)","type":"method"}],"path":"\/documentation\/messenger\/chatviewcontroller\/uiimagepickercontrollerdelegate-implementations","title":"UIImagePickerControllerDelegate Implementations","type":"symbol"}],"path":"\/documentation\/messenger\/chatviewcontroller","title":"ChatViewController","type":"class"},{"children":[{"title":"Initializers","type":"groupMarker"},{"path":"\/documentation\/messenger\/conversationtableviewcell\/init(coder:)","title":"init?(coder: NSCoder)","type":"init"},{"path":"\/documentation\/messenger\/conversationtableviewcell\/init(style:reuseidentifier:)","title":"init(style: UITableViewCell.CellStyle, reuseIdentifier: String?)","type":"init"},{"title":"Instance Methods","type":"groupMarker"},{"path":"\/documentation\/messenger\/conversationtableviewcell\/configure(with:)","title":"func configure(with: Conversation)","type":"method"},{"path":"\/documentation\/messenger\/conversationtableviewcell\/layoutsubviews()","title":"func layoutSubviews()","type":"method"},{"title":"Type Properties","type":"groupMarker"},{"path":"\/documentation\/messenger\/conversationtableviewcell\/identifier","title":"static let identifier: String","type":"property"}],"path":"\/documentation\/messenger\/conversationtableviewcell","title":"ConversationTableViewCell","type":"class"},{"children":[{"title":"Instance Methods","type":"groupMarker"},{"path":"\/documentation\/messenger\/conversationsviewcontroller\/openconversation(_:)","title":"func openConversation(Conversation)","type":"method"},{"path":"\/documentation\/messenger\/conversationsviewcontroller\/viewdidappear(_:)","title":"func viewDidAppear(Bool)","type":"method"},{"path":"\/documentation\/messenger\/conversationsviewcontroller\/viewdidload()","title":"func viewDidLoad()","type":"method"},{"path":"\/documentation\/messenger\/conversationsviewcontroller\/viewwillappear(_:)","title":"func viewWillAppear(Bool)","type":"method"},{"title":"Default Implementations","type":"groupMarker"},{"children":[{"title":"Instance Methods","type":"groupMarker"},{"path":"\/documentation\/messenger\/conversationsviewcontroller\/tableview(_:cellforrowat:)","title":"func tableView(UITableView, cellForRowAt: IndexPath) -> UITableViewCell","type":"method"},{"path":"\/documentation\/messenger\/conversationsviewcontroller\/tableview(_:commit:forrowat:)","title":"func tableView(UITableView, commit: UITableViewCell.EditingStyle, forRowAt: IndexPath)","type":"method"},{"path":"\/documentation\/messenger\/conversationsviewcontroller\/tableview(_:numberofrowsinsection:)","title":"func tableView(UITableView, numberOfRowsInSection: Int) -> Int","type":"method"}],"path":"\/documentation\/messenger\/conversationsviewcontroller\/uitableviewdatasource-implementations","title":"UITableViewDataSource Implementations","type":"symbol"},{"children":[{"title":"Instance Methods","type":"groupMarker"},{"path":"\/documentation\/messenger\/conversationsviewcontroller\/tableview(_:didselectrowat:)","title":"func tableView(UITableView, didSelectRowAt: IndexPath)","type":"method"},{"path":"\/documentation\/messenger\/conversationsviewcontroller\/tableview(_:editingstyleforrowat:)","title":"func tableView(UITableView, editingStyleForRowAt: IndexPath) -> UITableViewCell.EditingStyle","type":"method"},{"path":"\/documentation\/messenger\/conversationsviewcontroller\/tableview(_:heightforrowat:)","title":"func tableView(UITableView, heightForRowAt: IndexPath) -> CGFloat","type":"method"}],"path":"\/documentation\/messenger\/conversationsviewcontroller\/uitableviewdelegate-implementations","title":"UITableViewDelegate Implementations","type":"symbol"}],"path":"\/documentation\/messenger\/conversationsviewcontroller","title":"ConversationsViewController","type":"class"},{"children":[{"title":"Instance Methods","type":"groupMarker"},{"path":"\/documentation\/messenger\/databasemanager\/conversationexists(with:completion:)","title":"func conversationExists(with: String, completion: (Result<String, Error>) -> Void)","type":"method"},{"path":"\/documentation\/messenger\/databasemanager\/createnewconversation(with:name:firstmessage:completion:)","title":"func createNewConversation(with: String, name: String, firstMessage: Message, completion: (Bool) -> Void)","type":"method"},{"path":"\/documentation\/messenger\/databasemanager\/deleteconversation(conversationid:completion:)","title":"func deleteConversation(conversationID: String, completion: (Bool) -> Void)","type":"method"},{"path":"\/documentation\/messenger\/databasemanager\/getallconversations(for:completion:)","title":"func getAllConversations(for: String, completion: (Result<[Conversation], Error>) -> Void)","type":"method"},{"path":"\/documentation\/messenger\/databasemanager\/getallmessagsforconversations(with:completion:)","title":"func getAllMessagsForConversations(with: String, completion: (Result<[Message], Error>) -> Void)","type":"method"},{"path":"\/documentation\/messenger\/databasemanager\/getallusers(completion:)","title":"func getAllUsers(completion: (Result<[[String : String]], Error>) -> Void)","type":"method"},{"path":"\/documentation\/messenger\/databasemanager\/getdatafor(path:completion:)","title":"func getDataFor(path: String, completion: (Result<Any, Error>) -> Void)","type":"method"},{"path":"\/documentation\/messenger\/databasemanager\/insertuser(with:completion:)","title":"func insertUser(with: User, completion: (Bool) -> Void)","type":"method"},{"path":"\/documentation\/messenger\/databasemanager\/isregistered(with:completion:)","title":"func isRegistered(with: String, completion: ((Bool) -> Void))","type":"method"},{"path":"\/documentation\/messenger\/databasemanager\/sendmessage(to:otheruseremail:name:newmessage:completion:)","title":"func sendMessage(to: String, otherUserEmail: String, name: String, newMessage: Message, completion: (Bool) -> Void)","type":"method"},{"title":"Type Properties","type":"groupMarker"},{"path":"\/documentation\/messenger\/databasemanager\/shared","title":"static let shared: DatabaseManager","type":"property"},{"title":"Enumerations","type":"groupMarker"},{"children":[{"title":"Enumeration Cases","type":"groupMarker"},{"path":"\/documentation\/messenger\/databasemanager\/databaseerror\/failedtofetch","title":"case failedToFetch","type":"case"},{"title":"Instance Properties","type":"groupMarker"},{"path":"\/documentation\/messenger\/databasemanager\/databaseerror\/localizeddescription","title":"var localizedDescription: String","type":"property"},{"title":"Default Implementations","type":"groupMarker"},{"children":[{"title":"Operators","type":"groupMarker"},{"path":"\/documentation\/messenger\/databasemanager\/databaseerror\/!=(_:_:)","title":"static func != (Self, Self) -> Bool","type":"op"}],"path":"\/documentation\/messenger\/databasemanager\/databaseerror\/equatable-implementations","title":"Equatable Implementations","type":"symbol"}],"path":"\/documentation\/messenger\/databasemanager\/databaseerror","title":"DatabaseManager.DatabaseError","type":"enum"}],"path":"\/documentation\/messenger\/databasemanager","title":"DatabaseManager","type":"class"},{"children":[{"title":"Initializers","type":"groupMarker"},{"path":"\/documentation\/messenger\/locationpickerviewcontroller\/init(coder:)","title":"init?(coder: NSCoder)","type":"init"},{"path":"\/documentation\/messenger\/locationpickerviewcontroller\/init(coordinates:ispickable:)","title":"init(coordinates: CLLocationCoordinate2D?, isPickable: Bool)","type":"init"},{"title":"Instance Properties","type":"groupMarker"},{"path":"\/documentation\/messenger\/locationpickerviewcontroller\/completion","title":"var completion: ((CLLocationCoordinate2D) -> Void)?","type":"property"},{"title":"Instance Methods","type":"groupMarker"},{"path":"\/documentation\/messenger\/locationpickerviewcontroller\/viewdidload()","title":"func viewDidLoad()","type":"method"}],"path":"\/documentation\/messenger\/locationpickerviewcontroller","title":"LocationPickerViewController","type":"class"},{"children":[{"title":"Instance Methods","type":"groupMarker"},{"path":"\/documentation\/messenger\/loginviewcontroller\/presentloginerroralert()","title":"func presentLoginErrorAlert()","type":"method"},{"path":"\/documentation\/messenger\/loginviewcontroller\/viewdidlayoutsubviews()","title":"func viewDidLayoutSubviews()","type":"method"},{"path":"\/documentation\/messenger\/loginviewcontroller\/viewdidload()","title":"func viewDidLoad()","type":"method"},{"title":"Default Implementations","type":"groupMarker"},{"children":[{"title":"Instance Methods","type":"groupMarker"},{"path":"\/documentation\/messenger\/loginviewcontroller\/textfieldshouldreturn(_:)","title":"func textFieldShouldReturn(UITextField) -> Bool","type":"method"}],"path":"\/documentation\/messenger\/loginviewcontroller\/uitextfielddelegate-implementations","title":"UITextFieldDelegate Implementations","type":"symbol"}],"path":"\/documentation\/messenger\/loginviewcontroller","title":"LoginViewController","type":"class"},{"children":[{"title":"Initializers","type":"groupMarker"},{"path":"\/documentation\/messenger\/newconversationcell\/init(coder:)","title":"init?(coder: NSCoder)","type":"init"},{"path":"\/documentation\/messenger\/newconversationcell\/init(style:reuseidentifier:)","title":"init(style: UITableViewCell.CellStyle, reuseIdentifier: String?)","type":"init"},{"title":"Instance Methods","type":"groupMarker"},{"path":"\/documentation\/messenger\/newconversationcell\/configure(with:)","title":"func configure(with: SearchResult)","type":"method"},{"path":"\/documentation\/messenger\/newconversationcell\/layoutsubviews()","title":"func layoutSubviews()","type":"method"},{"title":"Type Properties","type":"groupMarker"},{"path":"\/documentation\/messenger\/newconversationcell\/identifier","title":"static let identifier: String","type":"property"}],"path":"\/documentation\/messenger\/newconversationcell","title":"NewConversationCell","type":"class"},{"children":[{"title":"Instance Properties","type":"groupMarker"},{"path":"\/documentation\/messenger\/newconversationviewcontroller\/completion","title":"var completion: ((SearchResult) -> Void)?","type":"property"},{"title":"Instance Methods","type":"groupMarker"},{"path":"\/documentation\/messenger\/newconversationviewcontroller\/filterusers(with:)","title":"func filterUsers(with: String)","type":"method"},{"path":"\/documentation\/messenger\/newconversationviewcontroller\/searchusers(query:)","title":"func searchUsers(query: String)","type":"method"},{"path":"\/documentation\/messenger\/newconversationviewcontroller\/updateui()","title":"func updateUI()","type":"method"},{"path":"\/documentation\/messenger\/newconversationviewcontroller\/viewdidload()","title":"func viewDidLoad()","type":"method"},{"title":"Default Implementations","type":"groupMarker"},{"children":[{"title":"Instance Methods","type":"groupMarker"},{"path":"\/documentation\/messenger\/newconversationviewcontroller\/searchbarsearchbuttonclicked(_:)","title":"func searchBarSearchButtonClicked(UISearchBar)","type":"method"}],"path":"\/documentation\/messenger\/newconversationviewcontroller\/uisearchbardelegate-implementations","title":"UISearchBarDelegate Implementations","type":"symbol"},{"children":[{"title":"Instance Methods","type":"groupMarker"},{"path":"\/documentation\/messenger\/newconversationviewcontroller\/tableview(_:cellforrowat:)","title":"func tableView(UITableView, cellForRowAt: IndexPath) -> UITableViewCell","type":"method"},{"path":"\/documentation\/messenger\/newconversationviewcontroller\/tableview(_:numberofrowsinsection:)","title":"func tableView(UITableView, numberOfRowsInSection: Int) -> Int","type":"method"}],"path":"\/documentation\/messenger\/newconversationviewcontroller\/uitableviewdatasource-implementations","title":"UITableViewDataSource Implementations","type":"symbol"},{"children":[{"title":"Instance Methods","type":"groupMarker"},{"path":"\/documentation\/messenger\/newconversationviewcontroller\/tableview(_:didselectrowat:)","title":"func tableView(UITableView, didSelectRowAt: IndexPath)","type":"method"},{"path":"\/documentation\/messenger\/newconversationviewcontroller\/tableview(_:heightforrowat:)","title":"func tableView(UITableView, heightForRowAt: IndexPath) -> CGFloat","type":"method"}],"path":"\/documentation\/messenger\/newconversationviewcontroller\/uitableviewdelegate-implementations","title":"UITableViewDelegate Implementations","type":"symbol"}],"path":"\/documentation\/messenger\/newconversationviewcontroller","title":"NewConversationViewController","type":"class"},{"children":[{"title":"Initializers","type":"groupMarker"},{"path":"\/documentation\/messenger\/photoviewerviewcontroller\/init(coder:)","title":"init?(coder: NSCoder)","type":"init"},{"path":"\/documentation\/messenger\/photoviewerviewcontroller\/init(with:)","title":"init(with: URL)","type":"init"},{"title":"Instance Methods","type":"groupMarker"},{"path":"\/documentation\/messenger\/photoviewerviewcontroller\/viewdidload()","title":"func viewDidLoad()","type":"method"}],"path":"\/documentation\/messenger\/photoviewerviewcontroller","title":"PhotoViewerViewController","type":"class"},{"children":[{"title":"Instance Methods","type":"groupMarker"},{"path":"\/documentation\/messenger\/profiletableviewcell\/setup(with:)","title":"func setup(with: ProfileViewModel)","type":"method"},{"title":"Type Properties","type":"groupMarker"},{"path":"\/documentation\/messenger\/profiletableviewcell\/identifier","title":"static let identifier: String","type":"property"}],"path":"\/documentation\/messenger\/profiletableviewcell","title":"ProfileTableViewCell","type":"class"},{"children":[{"title":"Instance Properties","type":"groupMarker"},{"path":"\/documentation\/messenger\/profileviewcontroller\/data","title":"var data: [ProfileViewModel]","type":"property"},{"path":"\/documentation\/messenger\/profileviewcontroller\/tableview","title":"var tableView: UITableView!","type":"property"},{"title":"Instance Methods","type":"groupMarker"},{"path":"\/documentation\/messenger\/profileviewcontroller\/createtableaheader()","title":"func createTableaHeader() -> UIView?","type":"method"},{"path":"\/documentation\/messenger\/profileviewcontroller\/viewdidload()","title":"func viewDidLoad()","type":"method"},{"path":"\/documentation\/messenger\/profileviewcontroller\/viewwillappear(_:)","title":"func viewWillAppear(Bool)","type":"method"},{"title":"Default Implementations","type":"groupMarker"},{"children":[{"title":"Instance Methods","type":"groupMarker"},{"path":"\/documentation\/messenger\/profileviewcontroller\/tableview(_:cellforrowat:)","title":"func tableView(UITableView, cellForRowAt: IndexPath) -> UITableViewCell","type":"method"},{"path":"\/documentation\/messenger\/profileviewcontroller\/tableview(_:numberofrowsinsection:)","title":"func tableView(UITableView, numberOfRowsInSection: Int) -> Int","type":"method"}],"path":"\/documentation\/messenger\/profileviewcontroller\/uitableviewdatasource-implementations","title":"UITableViewDataSource Implementations","type":"symbol"},{"children":[{"title":"Instance Methods","type":"groupMarker"},{"path":"\/documentation\/messenger\/profileviewcontroller\/tableview(_:didselectrowat:)","title":"func tableView(UITableView, didSelectRowAt: IndexPath)","type":"method"}],"path":"\/documentation\/messenger\/profileviewcontroller\/uitableviewdelegate-implementations","title":"UITableViewDelegate Implementations","type":"symbol"}],"path":"\/documentation\/messenger\/profileviewcontroller","title":"ProfileViewController","type":"class"},{"children":[{"title":"Instance Methods","type":"groupMarker"},{"path":"\/documentation\/messenger\/registerviewcontroller\/presentcamera()","title":"func presentCamera()","type":"method"},{"path":"\/documentation\/messenger\/registerviewcontroller\/presentphotoactionsheet()","title":"func presentPhotoActionSheet()","type":"method"},{"path":"\/documentation\/messenger\/registerviewcontroller\/presentphotopicker()","title":"func presentPhotoPicker()","type":"method"},{"path":"\/documentation\/messenger\/registerviewcontroller\/presentregistrationerroralert(message:)","title":"func presentRegistrationErrorAlert(message: String)","type":"method"},{"path":"\/documentation\/messenger\/registerviewcontroller\/viewdidlayoutsubviews()","title":"func viewDidLayoutSubviews()","type":"method"},{"path":"\/documentation\/messenger\/registerviewcontroller\/viewdidload()","title":"func viewDidLoad()","type":"method"},{"title":"Default Implementations","type":"groupMarker"},{"children":[{"title":"Instance Methods","type":"groupMarker"},{"path":"\/documentation\/messenger\/registerviewcontroller\/imagepickercontroller(_:didfinishpickingmediawithinfo:)","title":"func imagePickerController(UIImagePickerController, didFinishPickingMediaWithInfo: [UIImagePickerController.InfoKey : Any])","type":"method"},{"path":"\/documentation\/messenger\/registerviewcontroller\/imagepickercontrollerdidcancel(_:)","title":"func imagePickerControllerDidCancel(UIImagePickerController)","type":"method"}],"path":"\/documentation\/messenger\/registerviewcontroller\/uiimagepickercontrollerdelegate-implementations","title":"UIImagePickerControllerDelegate Implementations","type":"symbol"},{"children":[{"title":"Instance Methods","type":"groupMarker"},{"path":"\/documentation\/messenger\/registerviewcontroller\/textfieldshouldreturn(_:)","title":"func textFieldShouldReturn(UITextField) -> Bool","type":"method"}],"path":"\/documentation\/messenger\/registerviewcontroller\/uitextfielddelegate-implementations","title":"UITextFieldDelegate Implementations","type":"symbol"}],"path":"\/documentation\/messenger\/registerviewcontroller","title":"RegisterViewController","type":"class"},{"children":[{"title":"Instance Properties","type":"groupMarker"},{"path":"\/documentation\/messenger\/scenedelegate\/window","title":"var window: UIWindow?","type":"property"},{"title":"Instance Methods","type":"groupMarker"},{"path":"\/documentation\/messenger\/scenedelegate\/scene(_:willconnectto:options:)","title":"func scene(UIScene, willConnectTo: UISceneSession, options: UIScene.ConnectionOptions)","type":"method"}],"path":"\/documentation\/messenger\/scenedelegate","title":"SceneDelegate","type":"class"},{"children":[{"title":"Instance Methods","type":"groupMarker"},{"path":"\/documentation\/messenger\/storagemanager\/downloadurl(for:completion:)","title":"func downloadURL(for: String, completion: (Result<URL, Error>) -> Void)","type":"method"},{"path":"\/documentation\/messenger\/storagemanager\/uploadphoto(with:filename:completion:)","title":"func uploadPhoto(with: Data, fileName: String, completion: Completion)","type":"method"},{"path":"\/documentation\/messenger\/storagemanager\/uploadprofilepicture(with:filename:completion:)","title":"func uploadProfilePicture(with: Data, fileName: String, completion: Completion)","type":"method"},{"path":"\/documentation\/messenger\/storagemanager\/uploadvideo(with:filename:completion:)","title":"func uploadVideo(with: URL, fileName: String, completion: Completion)","type":"method"},{"title":"Type Aliases","type":"groupMarker"},{"path":"\/documentation\/messenger\/storagemanager\/completion","title":"StorageManager.Completion","type":"typealias"},{"title":"Type Properties","type":"groupMarker"},{"path":"\/documentation\/messenger\/storagemanager\/shared","title":"static let shared: StorageManager","type":"property"},{"title":"Enumerations","type":"groupMarker"},{"children":[{"title":"Enumeration Cases","type":"groupMarker"},{"path":"\/documentation\/messenger\/storagemanager\/storageerror\/failedtogetdownloadurl","title":"case failedToGetDownloadURL","type":"case"},{"path":"\/documentation\/messenger\/storagemanager\/storageerror\/failedtoupload","title":"case failedToUpload","type":"case"},{"title":"Default Implementations","type":"groupMarker"},{"children":[{"title":"Operators","type":"groupMarker"},{"path":"\/documentation\/messenger\/storagemanager\/storageerror\/!=(_:_:)","title":"static func != (Self, Self) -> Bool","type":"op"}],"path":"\/documentation\/messenger\/storagemanager\/storageerror\/equatable-implementations","title":"Equatable Implementations","type":"symbol"},{"children":[{"title":"Instance Properties","type":"groupMarker"},{"path":"\/documentation\/messenger\/storagemanager\/storageerror\/localizeddescription","title":"var localizedDescription: String","type":"property"}],"path":"\/documentation\/messenger\/storagemanager\/storageerror\/error-implementations","title":"Error Implementations","type":"symbol"}],"path":"\/documentation\/messenger\/storagemanager\/storageerror","title":"StorageManager.StorageError","type":"enum"}],"path":"\/documentation\/messenger\/storagemanager","title":"StorageManager","type":"class"},{"title":"Structures","type":"groupMarker"},{"children":[{"title":"Initializers","type":"groupMarker"},{"path":"\/documentation\/messenger\/colorresource\/init(name:bundle:)","title":"init(name: String, bundle: Bundle)","type":"init"},{"title":"Default Implementations","type":"groupMarker"},{"children":[{"title":"Operators","type":"groupMarker"},{"path":"\/documentation\/messenger\/colorresource\/!=(_:_:)","title":"static func != (Self, Self) -> Bool","type":"op"}],"path":"\/documentation\/messenger\/colorresource\/equatable-implementations","title":"Equatable Implementations","type":"symbol"}],"path":"\/documentation\/messenger\/colorresource","title":"ColorResource","type":"struct"},{"children":[{"title":"Initializers","type":"groupMarker"},{"path":"\/documentation\/messenger\/conversation\/init(id:name:otheruseremail:latestmessage:)","title":"init(id: String, name: String, otherUserEmail: String, latestMessage: LatestMessage)","type":"init"},{"title":"Instance Properties","type":"groupMarker"},{"path":"\/documentation\/messenger\/conversation\/id","title":"let id: String","type":"property"},{"path":"\/documentation\/messenger\/conversation\/latestmessage","title":"let latestMessage: LatestMessage","type":"property"},{"path":"\/documentation\/messenger\/conversation\/name","title":"let name: String","type":"property"},{"path":"\/documentation\/messenger\/conversation\/otheruseremail","title":"let otherUserEmail: String","type":"property"}],"path":"\/documentation\/messenger\/conversation","title":"Conversation","type":"struct"},{"children":[{"title":"Initializers","type":"groupMarker"},{"path":"\/documentation\/messenger\/imageresource\/init(name:bundle:)","title":"init(name: String, bundle: Bundle)","type":"init"},{"title":"Type Properties","type":"groupMarker"},{"path":"\/documentation\/messenger\/imageresource\/facebookmessengerlogo","title":"static let facebookMessengerLogo: ImageResource","type":"property"},{"title":"Default Implementations","type":"groupMarker"},{"children":[{"title":"Operators","type":"groupMarker"},{"path":"\/documentation\/messenger\/imageresource\/!=(_:_:)","title":"static func != (Self, Self) -> Bool","type":"op"}],"path":"\/documentation\/messenger\/imageresource\/equatable-implementations","title":"Equatable Implementations","type":"symbol"}],"path":"\/documentation\/messenger\/imageresource","title":"ImageResource","type":"struct"},{"children":[{"title":"Initializers","type":"groupMarker"},{"path":"\/documentation\/messenger\/latestmessage\/init(date:text:isread:)","title":"init(date: String, text: String, isRead: Bool)","type":"init"},{"title":"Instance Properties","type":"groupMarker"},{"path":"\/documentation\/messenger\/latestmessage\/date","title":"let date: String","type":"property"},{"path":"\/documentation\/messenger\/latestmessage\/isread","title":"let isRead: Bool","type":"property"},{"path":"\/documentation\/messenger\/latestmessage\/text","title":"let text: String","type":"property"}],"path":"\/documentation\/messenger\/latestmessage","title":"LatestMessage","type":"struct"},{"children":[{"title":"Initializers","type":"groupMarker"},{"path":"\/documentation\/messenger\/location\/init(location:size:)","title":"init(location: CLLocation, size: CGSize)","type":"init"},{"title":"Instance Properties","type":"groupMarker"},{"path":"\/documentation\/messenger\/location\/location","title":"var location: CLLocation","type":"property"},{"path":"\/documentation\/messenger\/location\/size","title":"var size: CGSize","type":"property"}],"path":"\/documentation\/messenger\/location","title":"Location","type":"struct"},{"children":[{"title":"Initializers","type":"groupMarker"},{"path":"\/documentation\/messenger\/media\/init(url:image:placeholderimage:size:)","title":"init(url: URL?, image: UIImage?, placeholderImage: UIImage, size: CGSize)","type":"init"},{"title":"Instance Properties","type":"groupMarker"},{"path":"\/documentation\/messenger\/media\/image","title":"var image: UIImage?","type":"property"},{"path":"\/documentation\/messenger\/media\/placeholderimage","title":"var placeholderImage: UIImage","type":"property"},{"path":"\/documentation\/messenger\/media\/size","title":"var size: CGSize","type":"property"},{"path":"\/documentation\/messenger\/media\/url","title":"var url: URL?","type":"property"}],"path":"\/documentation\/messenger\/media","title":"Media","type":"struct"},{"children":[{"title":"Initializers","type":"groupMarker"},{"path":"\/documentation\/messenger\/message\/init(sender:messageid:sentdate:kind:)","title":"init(sender: SenderType, messageId: String, sentDate: Date, kind: MessageKind)","type":"init"},{"title":"Instance Properties","type":"groupMarker"},{"path":"\/documentation\/messenger\/message\/kind","title":"var kind: MessageKind","type":"property"},{"path":"\/documentation\/messenger\/message\/messageid","title":"var messageId: String","type":"property"},{"path":"\/documentation\/messenger\/message\/sender","title":"var sender: SenderType","type":"property"},{"path":"\/documentation\/messenger\/message\/sentdate","title":"var sentDate: Date","type":"property"}],"path":"\/documentation\/messenger\/message","title":"Message","type":"struct"},{"children":[{"title":"Initializers","type":"groupMarker"},{"path":"\/documentation\/messenger\/profileviewmodel\/init(viewmodeltype:title:color:alignment:handler:)","title":"init(viewModelType: ProfileViewModelType, title: String, color: UIColor, alignment: NSTextAlignment, handler: (() -> Void)?)","type":"init"},{"title":"Instance Properties","type":"groupMarker"},{"path":"\/documentation\/messenger\/profileviewmodel\/alignment","title":"let alignment: NSTextAlignment","type":"property"},{"path":"\/documentation\/messenger\/profileviewmodel\/color","title":"let color: UIColor","type":"property"},{"path":"\/documentation\/messenger\/profileviewmodel\/handler","title":"let handler: (() -> Void)?","type":"property"},{"path":"\/documentation\/messenger\/profileviewmodel\/title","title":"let title: String","type":"property"},{"path":"\/documentation\/messenger\/profileviewmodel\/viewmodeltype","title":"let viewModelType: ProfileViewModelType","type":"property"}],"path":"\/documentation\/messenger\/profileviewmodel","title":"ProfileViewModel","type":"struct"},{"children":[{"title":"Initializers","type":"groupMarker"},{"path":"\/documentation\/messenger\/searchresult\/init(name:email:)","title":"init(name: String, email: String)","type":"init"},{"title":"Instance Properties","type":"groupMarker"},{"path":"\/documentation\/messenger\/searchresult\/email","title":"let email: String","type":"property"},{"path":"\/documentation\/messenger\/searchresult\/name","title":"let name: String","type":"property"}],"path":"\/documentation\/messenger\/searchresult","title":"SearchResult","type":"struct"},{"children":[{"title":"Initializers","type":"groupMarker"},{"path":"\/documentation\/messenger\/sender\/init(photourl:senderid:displayname:)","title":"init(photoURL: String, senderId: String, displayName: String)","type":"init"},{"title":"Instance Properties","type":"groupMarker"},{"path":"\/documentation\/messenger\/sender\/displayname","title":"var displayName: String","type":"property"},{"path":"\/documentation\/messenger\/sender\/photourl","title":"var photoURL: String","type":"property"},{"path":"\/documentation\/messenger\/sender\/senderid","title":"var senderId: String","type":"property"}],"path":"\/documentation\/messenger\/sender","title":"Sender","type":"struct"},{"children":[{"title":"Initializers","type":"groupMarker"},{"path":"\/documentation\/messenger\/user\/init(firstname:lastname:email:)","title":"init(firstName: String, lastName: String, email: String)","type":"init"},{"title":"Instance Properties","type":"groupMarker"},{"path":"\/documentation\/messenger\/user\/email","title":"let email: String","type":"property"},{"path":"\/documentation\/messenger\/user\/firstname","title":"let firstName: String","type":"property"},{"path":"\/documentation\/messenger\/user\/lastname","title":"let lastName: String","type":"property"},{"path":"\/documentation\/messenger\/user\/profilepicturefilename","title":"var profilePictureFileName: String","type":"property"},{"path":"\/documentation\/messenger\/user\/safeemail","title":"var safeEmail: String","type":"property"}],"path":"\/documentation\/messenger\/user","title":"User","type":"struct"},{"children":[{"title":"Initializers","type":"groupMarker"},{"path":"\/documentation\/messenger\/utility\/init()","title":"init()","type":"init"},{"title":"Type Methods","type":"groupMarker"},{"path":"\/documentation\/messenger\/utility\/replaceperiodandatwithhyphen(text:)","title":"static func replacePeriodAndAtWithHyphen(text: String) -> String","type":"method"}],"path":"\/documentation\/messenger\/utility","title":"Utility","type":"struct"},{"title":"Enumerations","type":"groupMarker"},{"children":[{"title":"Enumeration Cases","type":"groupMarker"},{"path":"\/documentation\/messenger\/profileviewmodeltype\/info","title":"case info","type":"case"},{"path":"\/documentation\/messenger\/profileviewmodeltype\/logout","title":"case logout","type":"case"},{"title":"Default Implementations","type":"groupMarker"},{"children":[{"title":"Operators","type":"groupMarker"},{"path":"\/documentation\/messenger\/profileviewmodeltype\/!=(_:_:)","title":"static func != (Self, Self) -> Bool","type":"op"}],"path":"\/documentation\/messenger\/profileviewmodeltype\/equatable-implementations","title":"Equatable Implementations","type":"symbol"}],"path":"\/documentation\/messenger\/profileviewmodeltype","title":"ProfileViewModelType","type":"enum"},{"title":"Extended Modules","type":"groupMarker"},{"children":[{"title":"Extended Types","type":"groupMarker"},{"children":[{"title":"Extended Structures","type":"groupMarker"},{"children":[{"title":"Type Properties","type":"groupMarker"},{"path":"\/documentation\/messenger\/foundation\/nsnotification\/name\/didloginnotification","title":"static let didLogInNotification: Notification.Name","type":"property"}],"path":"\/documentation\/messenger\/foundation\/nsnotification\/name","title":"NSNotification.Name","type":"extension"}],"path":"\/documentation\/messenger\/foundation\/nsnotification","title":"NSNotification","type":"extension"}],"path":"\/documentation\/messenger\/foundation","title":"Foundation","type":"extension"},{"children":[{"title":"Extended Enumerations","type":"groupMarker"},{"children":[{"title":"Instance Properties","type":"groupMarker"},{"path":"\/documentation\/messenger\/messagekit\/messagekind\/messagekindstring","title":"var messageKindString: String","type":"property"}],"path":"\/documentation\/messenger\/messagekit\/messagekind","title":"MessageKind","type":"extension"}],"path":"\/documentation\/messenger\/messagekit","title":"MessageKit","type":"extension"},{"children":[{"title":"Extended Structures","type":"groupMarker"},{"children":[{"title":"Initializers","type":"groupMarker"},{"path":"\/documentation\/messenger\/swiftui\/color\/init(_:)","title":"init(ColorResource)","type":"init"}],"path":"\/documentation\/messenger\/swiftui\/color","title":"Color","type":"extension"},{"children":[{"title":"Initializers","type":"groupMarker"},{"path":"\/documentation\/messenger\/swiftui\/image\/init(_:)","title":"init(ImageResource)","type":"init"}],"path":"\/documentation\/messenger\/swiftui\/image","title":"Image","type":"extension"}],"path":"\/documentation\/messenger\/swiftui","title":"SwiftUI","type":"extension"},{"children":[{"title":"Extended Classes","type":"groupMarker"},{"children":[{"title":"Initializers","type":"groupMarker"},{"path":"\/documentation\/messenger\/uikit\/uicolor\/init(resource:)","title":"init(resource: ColorResource)","type":"init"}],"path":"\/documentation\/messenger\/uikit\/uicolor","title":"UIColor","type":"extension"},{"children":[{"title":"Initializers","type":"groupMarker"},{"path":"\/documentation\/messenger\/uikit\/uiimage\/init(resource:)","title":"init(resource: ImageResource)","type":"init"}],"path":"\/documentation\/messenger\/uikit\/uiimage","title":"UIImage","type":"extension"},{"children":[{"title":"Instance Properties","type":"groupMarker"},{"path":"\/documentation\/messenger\/uikit\/uiview\/bottom","title":"var bottom: CGFloat","type":"property"},{"path":"\/documentation\/messenger\/uikit\/uiview\/height","title":"var height: CGFloat","type":"property"},{"path":"\/documentation\/messenger\/uikit\/uiview\/left","title":"var left: CGFloat","type":"property"},{"path":"\/documentation\/messenger\/uikit\/uiview\/right","title":"var right: CGFloat","type":"property"},{"path":"\/documentation\/messenger\/uikit\/uiview\/top","title":"var top: CGFloat","type":"property"},{"path":"\/documentation\/messenger\/uikit\/uiview\/width","title":"var width: CGFloat","type":"property"}],"path":"\/documentation\/messenger\/uikit\/uiview","title":"UIView","type":"extension"}],"path":"\/documentation\/messenger\/uikit","title":"UIKit","type":"extension"}],"path":"\/documentation\/messenger","title":"Messenger","type":"module"}]},"schemaVersion":{"major":0,"minor":1,"patch":1}}